rudi_node_read/rudi_node_reader.py
rudi_node_read/connectors/io_connector.py
rudi_node_read/connectors/io_rudi_node_read.py
rudi_node_read/rudi_types/rudi_const.py
rudi_node_read/rudi_types/rudi_contact.py
rudi_node_read/rudi_types/rudi_dates.py
rudi_node_read/rudi_types/rudi_dictionary_entry.py
rudi_node_read/rudi_types/rudi_geo.py
rudi_node_read/rudi_types/rudi_licence.py
rudi_node_read/rudi_types/rudi_media.py
rudi_node_read/rudi_types/rudi_meta.py
rudi_node_read/rudi_types/rudi_meta_misc.py
rudi_node_read/rudi_types/rudi_org.py
rudi_node_read/rudi_types/defaults/meta_defaults.py
rudi_node_read/utils/err.py
rudi_node_read/utils/file_utils.py
rudi_node_read/utils/jwt.py
rudi_node_read/utils/log.py
rudi_node_read/utils/serializable.py
rudi_node_read/utils/type_date.py
rudi_node_read/utils/type_dict.py
rudi_node_read/utils/type_list.py
rudi_node_read/utils/type_misc.py
rudi_node_read/utils/type_string.py
rudi_node_read/utils/typing_utils.py
rudi_node_read-0.4.0.dist-info/METADATA
rudi_node_read-0.4.0.dist-info/WHEEL
rudi_node_read-0.4.0.dist-info/top_level.txt
rudi_node_read-0.4.0.dist-info/RECORD
