Metadata-Version: 2.4
Name: rudi-node-read
Version: 0.4.0
Summary: Use the external API of a RUDI Producer node
Author-email: Olivier Martineau <olivier.martineau@irisa.fr>
Maintainer-email: Olivier Martineau <olivier.martineau@irisa.fr>
License-Expression: EUPL-1.2
Project-URL: Homepage, https://github.com/OlivierMartineau/rudi-node-read
Project-URL: Documentation, https://app.swaggerhub.com/apis/OlivierMartineau/RUDI-PRODUCER
Project-URL: Changelog, https://github.com/OlivierMartineau/rudi-node-read/blob/release/CHANGELOG.md
Project-URL: Repository, https://github.com/OlivierMartineau/rudi-node-read
Keywords: rudi-node-read,rudi-node-get,RUDI,producer node,RUDI node,rudinode,open-data,Univ. Rennes
Classifier: Programming Language :: Python :: 3.10
Classifier: Programming Language :: Python :: 3.11
Classifier: Programming Language :: Python :: 3.12
Classifier: Natural Language :: English
Classifier: Operating System :: OS Independent
Requires-Python: >=3.10
Requires-Dist: deepdiff
Requires-Dist: termcolor==3.1.0
Requires-Dist: chardet
Requires-Dist: puremagic
Provides-Extra: dev
Requires-Dist: backports.tarfile==1.2.0; extra == "dev"
Requires-Dist: black==25.1.0; extra == "dev"
Requires-Dist: build==1.3.0; extra == "dev"
Requires-Dist: commitizen==4.8.3; extra == "dev"
Requires-Dist: inflect==7.5.0; extra == "dev"
Requires-Dist: ipykernel==6.30.1; extra == "dev"
Requires-Dist: jaraco-collections==5.2.1; extra == "dev"
Requires-Dist: jaraco-functools==4.3.0; extra == "dev"
Requires-Dist: pip-chill==1.0.3; extra == "dev"
Requires-Dist: pip-upgrade-outdated==1.5; extra == "dev"
Requires-Dist: pip3-autoremove==2.0.0; extra == "dev"
Requires-Dist: pkginfo==1.12.1.2; extra == "dev"
Requires-Dist: pre-commit==4.3.0; extra == "dev"
Requires-Dist: pytest-cov==6.2.1; extra == "dev"
Requires-Dist: tomli==2.2.1; extra == "dev"
Requires-Dist: twine==6.1.0; extra == "dev"
